{
    "description": "",
    "developer": "Dark Fader",
    "files": [
        {
            "description": "release",
            "filename": "BallgameDX_Demo__(Gameboy).zip",
            "hash": {
                "md5": "1cf795ca81972213dfea1dbd9d891379b37d02c1",
                "sha1": "1cf795ca81972213dfea1dbd9d891379b37d02c1",
                "sha256": "9418375fe7d014bbc8f531584e8c19ba78afcd67e59ae7abe2f14b2e119df7cd"
            }
        },
        {
            "default": true,
            "filename": "BallgameDXDemo.gbc",
            "hash": {
                "md5": "49213b31b96ca152bcc2d229ae732f32",
                "sha1": "846a79fc7defdf0097ae7b8d87f54367479f79fd",
                "sha256": "b5814e8f37766b99d30b6773bc8fa1a0f7f9a6daf87d821f37c956cc5d1cb7be"
            },
            "playable": true
        }
    ],
    "platform": "GBC",
    "rom": "BallgameDXDemo.gbc",
    "screenshots": [
        "20110402_ballgamedx_demo.png"
    ],
    "slug": "BallgameDX-Demo",
    "title": "BallgameDX Demo",
    "typetag": "game"
}