{
    "description": "",
    "developer": "Capital",
    "files": [
        {
            "description": "release",
            "filename": "Capital_Intro_No__3__(Gameboy).ZIP",
            "hash": {
                "md5": "ecea8263ca10aa049685f19e31e7abcecfe03b2f",
                "sha1": "ecea8263ca10aa049685f19e31e7abcecfe03b2f",
                "sha256": "f7a09e155f69e132a7e5a7c2cbd86fcf5d06c275b6dcc4d60c0143e4dd926dbf"
            }
        },
        {
            "default": true,
            "filename": "cpl-i_03.gbc",
            "hash": {
                "md5": "6315f16896555d883a617a16d090b1cc",
                "sha1": "0ef7265784ee671570afcc84f45a060b46de0f14",
                "sha256": "03f8a8a33d6fd87cf37d1fb46288e4598e812c6cca4494ca29256eaf90cfe7a1"
            },
            "playable": true
        }
    ],
    "platform": "GBC",
    "rom": "cpl-i_03.gbc",
    "screenshots": [
        "20110402_capital_intro_no._3.gif"
    ],
    "slug": "capital-intro-no-3",
    "title": "Capital Intro No. 3",
    "typetag": "demo"
}