{
    "date": "1998-01-01",
    "developer": "Harry Mulder",
    "files": [
        {
            "description": "release",
            "filename": "HM-KIRBY.ZIP",
            "hash": {
                "md5": "f3ade42f4c5df4cde2b8592e20bc546906b27e4a",
                "sha1": "f3ade42f4c5df4cde2b8592e20bc546906b27e4a",
                "sha256": "41fc6bf1f43f873ea04d91d061ac5d9972d1bb30e578ba20727ebefa287bb9e0"
            }
        },
        {
            "default": true,
            "filename": "KIRBYXXL.GB",
            "hash": {
                "md5": "2b7f158b2e4569c8eab9bcac8ba36346",
                "sha1": "2ff1546dd30bc15ff9882730a00f9817c54eaaa5",
                "sha256": "96667d434a76142ed601f43ffb08b705ff424312f77dd3545b353187944f9faa"
            },
            "playable": true
        }
    ],
    "platform": "GB",
    "screenshots": [
        "269.png"
    ],
    "slug": "kirby-xxl",
    "title": "Kirby XXL",
    "typetag": "demo"
}