{
    "description": "Bad Knorfi has stolen the toys of little Jack. As Jack can\u2019t live without his toys, it\u2019s your quest to bring toys back before morning.",
    "developer": "9wires",
    "files": [
        {
            "description": "release",
            "filename": "ToyToy_v1.1_(Gameboy).zip",
            "hash": {
                "md5": "6831528ddd386c16795998e97bcf4734ae735d39",
                "sha1": "6831528ddd386c16795998e97bcf4734ae735d39",
                "sha256": "1e197619b2902805a249b2b6d8080096b5ad4441eca17069383c7445e4b6532d"
            }
        },
        {
            "default": true,
            "filename": "toytoy.gbc",
            "hash": {
                "md5": "1b2569ff8d1a7f6b5538a2ebacf3c1bd",
                "sha1": "9b9a5edd4003370e479b40ee71b79c2cc6fc1aac",
                "sha256": "d44edceeaef5f8c4c19f08042a0f8784dea7e32a7befeb78a54aad21e825ff60"
            },
            "playable": true
        }
    ],
    "platform": "GBC",
    "rom": "toytoy.gbc",
    "screenshots": [
        "20110402_toytoy.png"
    ],
    "slug": "toytoy-v1-1",
    "title": "ToyToy v1.1",
    "typetag": "game"
}