{
    "date": "2015-12-09",
    "developer": "Xephyr",
    "files": [
        {
            "description": "release",
            "filename": "touhou_gb_0.2.zip",
            "hash": {
                "md5": "ab95e9c4288778a4d686c8bd26f0a87e",
                "sha1": "6e638e6aacb6152bb4d7c25b35b226ea7149c4b2",
                "sha256": "e6ccf3be4fce82fa656601133bf270ff1686783bc22e0fc04afafad32481c0b0"
            }
        },
        {
            "default": true,
            "filename": "touhou_winter.gb",
            "hash": {
                "md5": "e3b26e181ce9ebb44e88663d503f7be3",
                "sha1": "1e54cdd675e31c36a3ef7ad2489d63628761114e",
                "sha256": "34e4972cd34b40742c527f049b6b7357a8f009003497cf3c4bdf134386cd433d"
            },
            "playable": true
        }
    ],
    "platform": "GB",
    "screenshots": [
        "touhou.png"
    ],
    "slug": "touhou-gb-version-02",
    "title": "Touhou GB (Version 0.2)",
    "typetag": "game"
}