{
    "description": "",
    "developer": "Unknown",
    "files": [
        {
            "description": "release",
            "filename": "Asteroids_Treasure_Hunt__(Gameboy).zip"
        },
        {
            "default": true,
            "filename": "AsteroidsTreasureHunt.gbc",
            "playable": true
        }
    ],
    "platform": "GBC",
    "rom": "AsteroidsTreasureHunt.gbc",
    "screenshots": [
        "20110402_asteroids_treasure_hunt.png"
    ],
    "slug": "asteroids-treasure-hunt",
    "title": "Asteroids Treasure Hunt",
    "typetag": "game"
}